arxiv_client/__about__.py
arxiv_client/__init__.py
arxiv_client/article.py
arxiv_client/category.py
arxiv_client/client.py
arxiv_client/link.py
arxiv_client/query.py
arxiv_client-0.3.2.dist-info/METADATA
arxiv_client-0.3.2.dist-info/WHEEL
arxiv_client-0.3.2.dist-info/licenses/LICENSE
arxiv_client-0.3.2.dist-info/RECORD
