Metadata-Version: 2.3
Name: arxiv-client
Version: 0.3.2
Summary: Python3 client for the arXiv API
Project-URL: Source, https://github.com/linjer/arxiv-client
Author: Jerry Lin
License: MIT License
License-File: LICENSE
Classifier: Development Status :: 4 - Beta
Classifier: Programming Language :: Python :: 3.10
Classifier: Programming Language :: Python :: 3.11
Classifier: Programming Language :: Python :: 3.12
Requires-Python: >=3.11
Requires-Dist: feedparser>=6.0.11
Requires-Dist: requests>=2.31.0
